{
  "tag" : "div",
  "classArray" : ["panel"],
  "attributesArray": {
    "id": "universite"
  },
  "chileds":[
    {
      "tag" : "div",
      "classArray" : ["panel_title"],
      "attributesArray ": {},
      "content" : "Universite : 1",
      "chileds":[]
    },
    {
      "tag" : "div",
      "classArray" : ["panel_content"],
      "attributesArray" : {},
      "chileds":[
        {
          "tag" : "div",
          "classArray" : ["progress"],
          "attributesArray" : {},
          "chileds":[
            {
              "tag" : "div",
              "classArray" : ["progress-bar"],
              "attributesArray" : {},
              "chileds":[]
            }
          ]
        },
        {
          "tag" : "span",
          "classArray" : ["universite_notif"],
          "attributesArray" : {},
          "chileds":[
          ]
        },
        {
          "tag" : "a",
          "classArray" : ["btn-right"],
          "attributesArray" : {
            "href":"#",
            "id":"universite_btn"
          },
          "content" : "Acheter",
          "chileds":[
          ]
        }
      ]
    }
  ]
}